ASCII_Menus/__init__.py
ascii_menus-1.0.0.dist-info/licenses/LICENSE
ascii_menus-1.0.0.dist-info/METADATA
ascii_menus-1.0.0.dist-info/WHEEL
ascii_menus-1.0.0.dist-info/top_level.txt
ascii_menus-1.0.0.dist-info/RECORD
