Metadata-Version: 2.4
Name: ASCII-Menus
Version: 1.0.0
Summary: A simple library for creating different interactive menus
Author-email: Noxatra <noxatr4@gmail.com>
License: MIT License
Project-URL: Homepage, https://github.com/Noxatr4/ASCII-Menus
Keywords: Termial,Interactive_Menus,Menus
Classifier: License :: OSI Approved :: MIT License
Classifier: Programming Language :: Python
Classifier: Programming Language :: Python :: 3
Requires-Python: >=3.13
License-File: LICENSE
Dynamic: license-file
